{"admiral graf spee.md":"BnmTjHIF","akashi.md":"BAG6mhW8","api-examples.md":"CRRh3xeI","ark royal (banquet guardian).md":"DWwVMK2m","atago (midsummer march).md":"RepnHkQ8","ayanami.md":"B3S3zMDc","belfast (iridescent rose).md":"DcMSOnGH","bismarck (majesty of the ironblood).md":"DwMJV4a4","black prince.md":"ncyxtfal","centaur (undine of the beach).md":"CdjIH0Dx","cleveland (gentry knight).md":"Dal2cMR7","deutschland (service time).md":"CipIIIsa","dunkerque (summer sucré).md":"B2eReA4R","eldridge (new year's handholding).md":"Yctjunws","eldridge.md":"B5eamT2D","emile bertin (côte d'azur).md":"CjAor7Jy","fubuki (music pixy).md":"BQ9iXofL","gneisenau.md":"Die8tcTf","graf zeppelin (beachside urd).md":"B0jRNyUS","honolulu (summer accident).md":"DLGi1xBs","honolulu.md":"D6hE-fJR","ibuki (wish of a snow goddess).md":"DrhR61vu","index.md":"BTEWNqNI","javelin (beach picnic!).md":"W1D-0iw6","javelin.md":"BvkZ9C6h","laffey (new year rabbit).md":"BYgKQ4rp","laffey.md":"BqHj3r3t","markdown-examples.md":"ediKJOVO","ning hai.md":"DF2BsaQ0","ping hai.md":"sZUfDITq","shōkaku.md":"CfSWcJM6","st. louis (splendor of spring).md":"Bbbx-awL","st. louis (tipsy snow).md":"B2e64GuR","tai yuan (clamorous tortoise).md":"DnMzWvQp","taihou (forbidden feast).md":"CFAvwuS4","tirpitz (snow-melting summer).md":"CfCtHVML","unicorn (amusement park date).md":"DCZjJIPo","vampire.md":"BxMrTUHN","yukikaze.md":"CI25-rSK","z23.md":"CSzbOZp-","z46 (first summer).md":"CN_6ViAw","zara.md":"x8r2Tzhi"}
