{"admiral graf spee.md":"BgLgZRRF","akashi.md":"XvkY5cva","api-examples.md":"DahR_rVx","ark royal (banquet guardian).md":"DjD4gym2","atago (midsummer march).md":"rYXo1V9n","ayanami.md":"BR6UpWsk","belfast (iridescent rose).md":"B0ZSm3QQ","bismarck (majesty of the ironblood).md":"B19S1zno","black prince.md":"CO1IO4UI","centaur (undine of the beach).md":"BZ55mgqr","cleveland (gentry knight).md":"D0bZhYK6","deutschland (service time).md":"Bg86n273","dunkerque (summer sucré).md":"BEwzmhmH","eldridge (new year's handholding).md":"DRYELMV5","eldridge.md":"o9dBtQWp","emile bertin (côte d'azur).md":"Cj_7WC_I","fubuki (music pixy).md":"CC_-QbpE","gneisenau.md":"wjjcVvKc","graf zeppelin (beachside urd).md":"BsayADWf","honolulu (summer accident).md":"BnVuiONi","honolulu.md":"CtxHnGeo","ibuki (wish of a snow goddess).md":"Bj1YBHdy","index.md":"-EJgLuei","javelin (beach picnic!).md":"BCFkhKvv","javelin.md":"bw9kEXrM","laffey (new year rabbit).md":"DeUP72GP","laffey.md":"DiUQLtsE","ning hai.md":"DduI2rNF","ping hai.md":"B8sqrgmU","shōkaku.md":"CWo6yIMo","st. louis (splendor of spring).md":"DWwIuJAD","st. louis (tipsy snow).md":"CjdTzeam","tai yuan (clamorous tortoise).md":"D9NRG3PQ","taihou (forbidden feast).md":"C-4JV8tn","tirpitz (snow-melting summer).md":"DjG_3unC","unicorn (amusement park date).md":"Dn6ti2i1","vampire.md":"Dnp334N8","yukikaze.md":"DHh657I_","z23.md":"D_7QDyVP","z46 (first summer).md":"Dh51Fm8m","zara.md":"BtzGoLK1"}
